LICENSE
MANIFEST.in
requirements.txt
setup.cfg
setup.py
test_requirements.txt
erc20_demurrage_token/__init__.py
erc20_demurrage_token/demurrage.py
erc20_demurrage_token/expiry.py
erc20_demurrage_token/seal.py
erc20_demurrage_token/token.py
erc20_demurrage_token.egg-info/PKG-INFO
erc20_demurrage_token.egg-info/SOURCES.txt
erc20_demurrage_token.egg-info/dependency_links.txt
erc20_demurrage_token.egg-info/entry_points.txt
erc20_demurrage_token.egg-info/requires.txt
erc20_demurrage_token.egg-info/top_level.txt
erc20_demurrage_token/data/.chainlib
erc20_demurrage_token/data/DemurrageTokenSingleNocap.bin
erc20_demurrage_token/data/DemurrageTokenSingleNocap.json
erc20_demurrage_token/data/DemurrageTokenSingleNocap.metadata.json
erc20_demurrage_token/data/__init__.py
erc20_demurrage_token/data/config/eth.ini
erc20_demurrage_token/data/config/session.ini
erc20_demurrage_token/data/config/token.ini
erc20_demurrage_token/runnable/publish.py
erc20_demurrage_token/sim/__init__.py
erc20_demurrage_token/sim/error.py
erc20_demurrage_token/sim/sim.py
erc20_demurrage_token/unittest/__init__.py
erc20_demurrage_token/unittest/base.py
erc20_demurrage_token/unittest/newbase.py
man/build/erc20-demurrage-token-publish.1
tests/test_amounts.py
tests/test_basic.py
tests/test_burn.py
tests/test_cap.py
tests/test_expiry.py
tests/test_growth.py
tests/test_mint.py
tests/test_period.py
tests/test_redistribution_single.py
tests/test_redistribution_unit.py
tests/test_seal.py
tests/test_single.py