Metadata-Version: 2.1
Name: erc20-demurrage-token
Version: 0.5.6
Summary: ERC20 token with redistributed continual demurrage
Home-page: https://holbrook.no/src/erc20-demurrage-token/log.html
Author: Louis Holbrook
Author-email: dev@holbrook.no
License: AGPLv3+
Keywords: ethereum,blockchain,cryptocurrency,erc20
Classifier: Programming Language :: Python :: 3
Classifier: Operating System :: OS Independent
Classifier: Development Status :: 4 - Beta
Classifier: Environment :: Console
Classifier: Intended Audience :: Developers
Classifier: License :: OSI Approved :: GNU Affero General Public License v3 or later (AGPLv3+)
Classifier: Topic :: Internet
Classifier: Topic :: Software Development :: Libraries
Requires-Python: >=3.8
License-File: LICENSE
